{
	"format_version": "1.12.0",
	"minecraft:geometry": [
		{
			"description": {
				"identifier": "geometry.scope_standard_8x - Converted",
				"texture_width": 32,
				"texture_height": 32,
				"visible_bounds_width": 22,
				"visible_bounds_height": 9,
				"visible_bounds_offset": [0, 0.5, 0]
			},
			"bones": [
				{
					"name": "lod",
					"pivot": [0, 7.45, 0.875],
					"cubes": [
						{
							"origin": [-1, 0.95, -0.125],
							"size": [2, 2, 4.0625],
							"pivot": [0, 1.95, 0.875],
							"rotation": [0, 0, 45],
							"uv": {
								"north": {"uv": [11, 8], "uv_size": [2, 2]},
								"east": {"uv": [8, 0], "uv_size": [4, 2]},
								"south": {"uv": [11, 10], "uv_size": [2, 2]},
								"west": {"uv": [8, 2], "uv_size": [4, 2]},
								"up": {"uv": [4, 8], "uv_size": [2, 4]},
								"down": {"uv": [6, 12], "uv_size": [2, -4]}
							}
						},
						{
							"origin": [-1.125, 0.825, 0.125],
							"size": [2.25, 2.25, 0.75],
							"pivot": [0, 1.95, 0.875],
							"rotation": [0, 0, 45],
							"uv": {
								"north": {"uv": [8, 8], "uv_size": [2.5, 2]},
								"east": {"uv": [4, 14], "uv_size": [1, 2]},
								"south": {"uv": [10, 4], "uv_size": [2.5, 2]},
								"west": {"uv": [5, 14], "uv_size": [1, 2]},
								"up": {"uv": [4, 13], "uv_size": [2.5, 1]},
								"down": {"uv": [13, 5], "uv_size": [2.5, -1]}
							}
						},
						{
							"origin": [-1.125, 0.825, 2.5625],
							"size": [2.25, 2.25, 0.75],
							"pivot": [0, 1.95, 0.875],
							"rotation": [0, 0, 45],
							"uv": {
								"north": {"uv": [10, 6], "uv_size": [2.5, 2]},
								"east": {"uv": [6, 14], "uv_size": [1, 2]},
								"south": {"uv": [8, 10], "uv_size": [2.5, 2]},
								"west": {"uv": [2, 15], "uv_size": [1, 2]},
								"up": {"uv": [13, 5], "uv_size": [2.5, 1]},
								"down": {"uv": [13, 7], "uv_size": [2.5, -1]}
							}
						},
						{
							"origin": [-0.75, 1.2, -7.9375],
							"size": [1.5, 1.5, 7.8125],
							"pivot": [0, 1.95, 0.875],
							"rotation": [0, 0, 45],
							"uv": {
								"north": {"uv": [7, 13], "uv_size": [1.5, 1.5]},
								"east": {"uv": [0, 0], "uv_size": [8, 1.5]},
								"south": {"uv": [13, 7], "uv_size": [1.5, 1.5]},
								"west": {"uv": [0, 2], "uv_size": [8, 1.5]},
								"up": {"uv": [0, 4], "uv_size": [1.5, 8]},
								"down": {"uv": [2, 12], "uv_size": [1.5, -8]}
							}
						},
						{
							"origin": [-0.875, 1.075, -1.625],
							"size": [1.75, 1.75, 0.8125],
							"pivot": [0, 1.95, 0.875],
							"rotation": [0, 0, 45],
							"uv": {
								"north": {"uv": [0, 12], "uv_size": [2, 1.5]},
								"east": {"uv": [3, 15], "uv_size": [1, 1.5]},
								"south": {"uv": [12, 0], "uv_size": [2, 1.5]},
								"west": {"uv": [7, 15], "uv_size": [1, 1.5]},
								"up": {"uv": [13, 11], "uv_size": [2, 1]},
								"down": {"uv": [2, 15], "uv_size": [2, -1]}
							}
						},
						{
							"origin": [-0.875, 1.075, -5.375],
							"size": [1.75, 1.75, 0.8125],
							"pivot": [0, 1.95, 0.875],
							"rotation": [0, 0, 45],
							"uv": {
								"north": {"uv": [2, 12], "uv_size": [2, 1.5]},
								"east": {"uv": [15, 7], "uv_size": [1, 1.5]},
								"south": {"uv": [12, 2], "uv_size": [2, 1.5]},
								"west": {"uv": [8, 15], "uv_size": [1, 1.5]},
								"up": {"uv": [14, 2], "uv_size": [2, 1]},
								"down": {"uv": [14, 4], "uv_size": [2, -1]}
							}
						},
						{
							"origin": [0.25, 1.2625, -3],
							"size": [1.4375, 1.4375, 0.375],
							"pivot": [0.9375, 1.95, -3.03125],
							"rotation": [90, 45, 90],
							"uv": {
								"north": {"uv": [9, 13], "uv_size": [1.5, 1.5]},
								"east": {"uv": [12, 15], "uv_size": [0.5, 1.5]},
								"south": {"uv": [13, 9], "uv_size": [1.5, 1.5]},
								"west": {"uv": [13, 15], "uv_size": [0.5, 1.5]},
								"up": {"uv": [15, 11], "uv_size": [1.5, 0.5]},
								"down": {"uv": [15, 13.5], "uv_size": [1.5, -0.5]}
							}
						},
						{
							"origin": [-0.6875, 2.1375, -3],
							"size": [1.4375, 1.4375, 0.375],
							"pivot": [0, 2.825, -3.03125],
							"rotation": [90, 45, 0],
							"uv": {
								"north": {"uv": [0, 14], "uv_size": [1.5, 1.5]},
								"east": {"uv": [16, 1], "uv_size": [0.5, 1.5]},
								"south": {"uv": [14, 0], "uv_size": [1.5, 1.5]},
								"west": {"uv": [16, 3], "uv_size": [0.5, 1.5]},
								"up": {"uv": [4, 16], "uv_size": [1.5, 0.5]},
								"down": {"uv": [16, 5.5], "uv_size": [1.5, -0.5]}
							}
						},
						{
							"origin": [-3.71875, -0.425, -3.45044],
							"size": [5.875, 1.4375, 0.4375],
							"pivot": [0, 0.29375, -3.07544],
							"rotation": [0, 90, -90],
							"uv": {
								"north": {"uv": [4, 4], "uv_size": [6, 1.5]},
								"east": {"uv": [6, 16], "uv_size": [0.5, 1.5]},
								"south": {"uv": [4, 6], "uv_size": [6, 1.5]},
								"west": {"uv": [16, 6], "uv_size": [0.5, 1.5]},
								"up": {"uv": [4, 12], "uv_size": [6, 0.5]},
								"down": {"uv": [10, 12.5], "uv_size": [6, -0.5]}
							}
						},
						{
							"origin": [0.5625, -0.1125, 0.01831],
							"size": [0.625, 0.3125, 0.625],
							"pivot": [0.875, 0.04375, 0.33081],
							"rotation": [-180, 45, 90],
							"uv": {
								"north": {"uv": [17, 1], "uv_size": [0.5, 0.5]},
								"east": {"uv": [2, 17], "uv_size": [0.5, 0.5]},
								"south": {"uv": [17, 2], "uv_size": [0.5, 0.5]},
								"west": {"uv": [3, 17], "uv_size": [0.5, 0.5]},
								"up": {"uv": [17, 3], "uv_size": [0.5, 0.5]},
								"down": {"uv": [4, 17.5], "uv_size": [0.5, -0.5]}
							}
						},
						{
							"origin": [0.5625, -0.1125, -3.29419],
							"size": [0.625, 0.3125, 0.625],
							"pivot": [0.875, 0.04375, -2.98169],
							"rotation": [-180, 45, 90],
							"uv": {
								"north": {"uv": [17, 4], "uv_size": [0.5, 0.5]},
								"east": {"uv": [5, 17], "uv_size": [0.5, 0.5]},
								"south": {"uv": [17, 6], "uv_size": [0.5, 0.5]},
								"west": {"uv": [7, 17], "uv_size": [0.5, 0.5]},
								"up": {"uv": [17, 7], "uv_size": [0.5, 0.5]},
								"down": {"uv": [8, 17.5], "uv_size": [0.5, -0.5]}
							}
						},
						{
							"origin": [-2.28125, -0.175, -3.26294],
							"size": [0.8125, 1.4375, 0.875],
							"pivot": [0, 0.54375, -3.07544],
							"rotation": [0, 90, -90],
							"uv": {
								"north": {"uv": [9, 15], "uv_size": [1, 1.5]},
								"east": {"uv": [16, 8], "uv_size": [0.5, 1.5]},
								"south": {"uv": [15, 9], "uv_size": [1, 1.5]},
								"west": {"uv": [16, 14], "uv_size": [0.5, 1.5]},
								"up": {"uv": [16, 10], "uv_size": [1, 0.5]},
								"down": {"uv": [16, 12.5], "uv_size": [1, -0.5]}
							}
						},
						{
							"origin": [-2.28125, -0.175, -6.88794],
							"size": [0.8125, 1.4375, 0.875],
							"pivot": [0, 0.54375, -6.70044],
							"rotation": [0, 90, -90],
							"uv": {
								"north": {"uv": [10, 15], "uv_size": [1, 1.5]},
								"east": {"uv": [15, 16], "uv_size": [0.5, 1.5]},
								"south": {"uv": [11, 15], "uv_size": [1, 1.5]},
								"west": {"uv": [16, 16], "uv_size": [0.5, 1.5]},
								"up": {"uv": [0, 17], "uv_size": [1, 0.5]},
								"down": {"uv": [1, 17.5], "uv_size": [1, -0.5]}
							}
						},
						{
							"origin": [-1.625, 1.2625, -3.4375],
							"size": [1.4375, 1.4375, 0.4375],
							"pivot": [-0.9375, 1.95, -3.03125],
							"rotation": [90, 45, 90],
							"uv": {
								"north": {"uv": [11, 13], "uv_size": [1.5, 1.5]},
								"east": {"uv": [14, 15], "uv_size": [0.5, 1.5]},
								"south": {"uv": [13, 13], "uv_size": [1.5, 1.5]},
								"west": {"uv": [15, 14], "uv_size": [0.5, 1.5]},
								"up": {"uv": [0, 16], "uv_size": [1.5, 0.5]},
								"down": {"uv": [16, 0.5], "uv_size": [1.5, -0.5]}
							}
						}
					]
				}
			]
		}
	]
}