{
	"format_version": "1.12.0",
	"minecraft:geometry": [
		{
			"description": {
				"identifier": "geometry.556x45 - Converted",
				"texture_width": 16,
				"texture_height": 16,
				"visible_bounds_width": 2,
				"visible_bounds_height": 1.5,
				"visible_bounds_offset": [0, 0.25, 0]
			},
			"bones": [
				{
					"name": "556x45",
					"pivot": [8, 0, -8],
					"cubes": [
						{
							"origin": [-0.20313, -0.79053, -0.20312],
							"size": [0.40625, 1.525, 0.40625],
							"pivot": [0, 0, 0],
							"rotation": [90, 0, 0],
							"uv": {
								"north": {"uv": [0, 0], "uv_size": [0.25, 0.75]},
								"east": {"uv": [1, 0], "uv_size": [0.25, 0.75]},
								"south": {"uv": [0, 1.5], "uv_size": [0.25, 0.75]},
								"west": {"uv": [1, 1.5], "uv_size": [0.25, 0.75]},
								"up": {"uv": [2, 0], "uv_size": [0.25, 0.25]},
								"down": {"uv": [2, 1.25], "uv_size": [0.25, -0.25]}
							}
						},
						{
							"origin": [-0.14453, 0.72119, -0.14453],
							"size": [0.28906, 0.40235, 0.28906],
							"pivot": [0, 0, 0],
							"rotation": [90, 0, 0],
							"uv": {
								"north": {"uv": [2, 2], "uv_size": [0.25, 0.25]},
								"east": {"uv": [0, 3], "uv_size": [0.25, 0.25]},
								"south": {"uv": [3, 0], "uv_size": [0.25, 0.25]},
								"west": {"uv": [1, 3], "uv_size": [0.25, 0.25]},
								"up": {"uv": [3, 1], "uv_size": [0.25, 0.25]},
								"down": {"uv": [2, 3.25], "uv_size": [0.25, -0.25]}
							}
						},
						{
							"origin": [-0.20313, -0.9663, -0.20312],
							"size": [0.40625, 0.08788, 0.40625],
							"pivot": [0, 0, 0],
							"rotation": [90, 0, 0],
							"uv": {
								"north": {"uv": [1, 6], "uv_size": [0.25, 0.25]},
								"east": {"uv": [6, 1], "uv_size": [0.25, 0.25]},
								"south": {"uv": [2, 6], "uv_size": [0.25, 0.25]},
								"west": {"uv": [6, 2], "uv_size": [0.25, 0.25]},
								"up": {"uv": [3, 6], "uv_size": [0.25, 0.25]},
								"down": {"uv": [6, 3.25], "uv_size": [0.25, -0.25]}
							}
						},
						{
							"origin": [-0.14453, -0.90771, -0.14453],
							"size": [0.28906, 0.11719, 0.28906],
							"pivot": [0, 0, 0],
							"rotation": [90, 0, 0],
							"uv": {
								"north": {"uv": [4, 6], "uv_size": [0.25, 0.25]},
								"east": {"uv": [6, 4], "uv_size": [0.25, 0.25]},
								"south": {"uv": [5, 6], "uv_size": [0.25, 0.25]},
								"west": {"uv": [6, 5], "uv_size": [0.25, 0.25]},
								"up": {"uv": [6, 6], "uv_size": [0.25, 0.25]},
								"down": {"uv": [0, 7.25], "uv_size": [0.25, -0.25]}
							}
						},
						{
							"origin": [-0.46782, 0.59939, -0.14453],
							"size": [0.10156, 0.15234, 0.28906],
							"pivot": [0, 0, 0],
							"rotation": [90, -22.5, 0],
							"uv": {
								"north": {"uv": [7, 0], "uv_size": [0.25, 0.25]},
								"east": {"uv": [1, 7], "uv_size": [0.25, 0.25]},
								"south": {"uv": [7, 1], "uv_size": [0.25, 0.25]},
								"west": {"uv": [2, 7], "uv_size": [0.25, 0.25]},
								"up": {"uv": [7, 2], "uv_size": [0.25, 0.25]},
								"down": {"uv": [3, 7.25], "uv_size": [0.25, -0.25]}
							}
						},
						{
							"origin": [-0.14453, 0.59939, 0.36626],
							"size": [0.28906, 0.15234, 0.10156],
							"pivot": [0, 0, 0],
							"rotation": [112.5, 0, 0],
							"uv": {
								"north": {"uv": [7, 3], "uv_size": [0.25, 0.25]},
								"east": {"uv": [4, 7], "uv_size": [0.25, 0.25]},
								"south": {"uv": [7, 4], "uv_size": [0.25, 0.25]},
								"west": {"uv": [5, 7], "uv_size": [0.25, 0.25]},
								"up": {"uv": [7, 5], "uv_size": [0.25, 0.25]},
								"down": {"uv": [6, 7.25], "uv_size": [0.25, -0.25]}
							}
						},
						{
							"origin": [-0.14453, 0.59939, -0.46782],
							"size": [0.28906, 0.15234, 0.10156],
							"pivot": [0, 0, 0],
							"rotation": [67.5, 0, 0],
							"uv": {
								"north": {"uv": [7, 6], "uv_size": [0.25, 0.25]},
								"east": {"uv": [7, 7], "uv_size": [0.25, 0.25]},
								"south": {"uv": [0, 8], "uv_size": [0.25, 0.25]},
								"west": {"uv": [8, 0], "uv_size": [0.25, 0.25]},
								"up": {"uv": [1, 8], "uv_size": [0.25, 0.25]},
								"down": {"uv": [8, 1.25], "uv_size": [0.25, -0.25]}
							}
						},
						{
							"origin": [0.36626, 0.59939, -0.14453],
							"size": [0.10156, 0.15234, 0.28906],
							"pivot": [0, 0, 0],
							"rotation": [90, 22.5, 0],
							"uv": {
								"north": {"uv": [2, 8], "uv_size": [0.25, 0.25]},
								"east": {"uv": [8, 2], "uv_size": [0.25, 0.25]},
								"south": {"uv": [3, 8], "uv_size": [0.25, 0.25]},
								"west": {"uv": [8, 3], "uv_size": [0.25, 0.25]},
								"up": {"uv": [4, 8], "uv_size": [0.25, 0.25]},
								"down": {"uv": [8, 4.25], "uv_size": [0.25, -0.25]}
							}
						}
					]
				}
			]
		}
	]
}